{
  "name": "WikiMind Calories",
  "short_name": "WM Calories",
  "description": "Suivi calorique et nutrition assisté par IA (WikiMind 3.0)",
  "start_url": "./Wikimind_calories.html",
  "display": "standalone",
  "background_color": "#050505",
  "theme_color": "#050505",
  "orientation": "portrait-primary",
  "icons": [
    {
      "src": "192pixels.png",
      "sizes": "192x192",
      "type": "image/png"
    },
    {
      "src": "512pixels.png",
      "sizes": "512x512",
      "type": "image/png"
    }
  ]
}